TubeKit/__init__.py
TubeKit/client.py
tubekit-0.1.5.dist-info/METADATA
tubekit-0.1.5.dist-info/WHEEL
tubekit-0.1.5.dist-info/RECORD
